segmented/__init__.py
segmented/bayes.py
segmented/demo.py
segmented/frequentist.py
segmented/version.py
segmented-0.0.6.dist-info/LICENSE.txt
segmented-0.0.6.dist-info/METADATA
segmented-0.0.6.dist-info/WHEEL
segmented-0.0.6.dist-info/top_level.txt
segmented-0.0.6.dist-info/RECORD
