Metadata-Version: 2.1
Name: segmented
Version: 0.0.6
Summary: segmented: A toolbox for segmented regression.
Home-page: http://github.com/cluhmann/segmented
Maintainer: Christian Luhmann <cluhmann@gmail.com>
Maintainer-email: cluhmann@gmail.com
License: MIT
Platform: UNKNOWN
License-File: LICENSE.txt
Requires-Dist: arviz (>=0.11.2)
Requires-Dist: emcee (>=3.0.0)
Requires-Dist: numpy (>=1.15.0)
Requires-Dist: pandas (>=0.24.0)
Requires-Dist: patsy (>=0.5.1)
Requires-Dist: scipy (>=1.4.1)
